pyglet_cornerpin/__init__.py
pyglet_cornerpin/cornerpin.py
pyglet_cornerpin-0.3.2.dist-info/METADATA
pyglet_cornerpin-0.3.2.dist-info/WHEEL
pyglet_cornerpin-0.3.2.dist-info/RECORD
