Metadata-Version: 2.1
Name: pyglet-cornerpin
Version: 0.3.2
Summary: Add a corner pin transform to a pyglet window
Home-page: https://git.rubenvandeven.com/r/pyglet-cornerpin
License: MIT
Author: Ruben van de Ven
Author-email: git@rubenvandeven.com
Requires-Python: >=3.10,<4.0
Classifier: License :: OSI Approved :: MIT License
Classifier: Programming Language :: Python :: 3
Classifier: Programming Language :: Python :: 3.10
Classifier: Programming Language :: Python :: 3.11
Classifier: Programming Language :: Python :: 3.12
Requires-Dist: pyglet (>=2.0.18,<3.0.0)
Project-URL: Repository, https://git.rubenvandeven.com/r/pyglet-cornerpin
